{
	"m-4": {
		"style": {
			"marginTop": 16,
			"marginRight": 16,
			"marginBottom": 16,
			"marginLeft": 16
		}
	},
	"m-1": {
		"style": {
			"marginTop": 4,
			"marginRight": 4,
			"marginBottom": 4,
			"marginLeft": 4
		}
	},
	"mx-8": {
		"style": {
			"marginLeft": 32,
			"marginRight": 32
		}
	},
	"mx-4": {
		"style": {
			"marginLeft": 16,
			"marginRight": 16
		}
	},
	"mx-1": {
		"style": {
			"marginLeft": 4,
			"marginRight": 4
		}
	},
	"mt-4": {
		"style": {
			"marginTop": 16
		}
	},
	"mr-2": {
		"style": {
			"marginRight": 8
		}
	},
	"ml-2": {
		"style": {
			"marginLeft": 8
		}
	},
	"h-40": {
		"style": {
			"height": 160
		}
	},
	"w-full": {
		"style": {
			"width": "100%"
		}
	},
	"w-40": {
		"style": {
			"width": 160
		}
	},
	"flex-1": {
		"style": {
			"flexGrow": 1,
			"flexShrink": 1,
			"flexBasis": "0%"
		}
	},
	"flex-row": {
		"style": {
			"flexDirection": "row"
		}
	},
	"items-center": {
		"style": {
			"alignItems": "center"
		}
	},
	"justify-center": {
		"style": {
			"justifyContent": "center"
		}
	},
	"justify-evenly": {
		"style": {
			"justifyContent": "space-evenly"
		}
	},
	"rounded-xl": {
		"style": {
			"borderTopLeftRadius": 12,
			"borderTopRightRadius": 12,
			"borderBottomRightRadius": 12,
			"borderBottomLeftRadius": 12
		}
	},
	"rounded-2xl": {
		"style": {
			"borderTopLeftRadius": 16,
			"borderTopRightRadius": 16,
			"borderBottomRightRadius": 16,
			"borderBottomLeftRadius": 16
		}
	},
	"bg-white": {
		"style": {
			"--tw-bg-opacity": 1,
			"backgroundColor": "rgb(255 255 255 / var(--tw-bg-opacity))"
		}
	},
	"bg-primary-200": {
		"style": {
			"--tw-bg-opacity": 1,
			"backgroundColor": "rgb(247 246 255 / var(--tw-bg-opacity))"
		}
	},
	"bg-primary": {
		"style": {
			"--tw-bg-opacity": 1,
			"backgroundColor": "rgb(138 79 255 / var(--tw-bg-opacity))"
		}
	},
	"bg-gray": {
		"style": {
			"--tw-bg-opacity": 1,
			"backgroundColor": "rgb(245 245 245 / var(--tw-bg-opacity))"
		}
	},
	"px-2": {
		"style": {
			"paddingLeft": 8,
			"paddingRight": 8
		}
	},
	"py-3": {
		"style": {
			"paddingTop": 12,
			"paddingBottom": 12
		}
	},
	"px-4": {
		"style": {
			"paddingLeft": 16,
			"paddingRight": 16
		}
	},
	"px-6": {
		"style": {
			"paddingLeft": 24,
			"paddingRight": 24
		}
	},
	"px-8": {
		"style": {
			"paddingLeft": 32,
			"paddingRight": 32
		}
	},
	"py-2": {
		"style": {
			"paddingTop": 8,
			"paddingBottom": 8
		}
	},
	"text-center": {
		"style": {
			"textAlign": "center"
		}
	},
	"font-wRegular": {
		"style": {
			"fontFamily": "WorkSans_400Regular"
		}
	},
	"text-lg": {
		"style": {
			"fontSize": 18,
			"lineHeight": 28
		}
	},
	"text-base": {
		"style": {
			"fontSize": 16,
			"lineHeight": 24
		}
	},
	"text-primary-400": {
		"style": {
			"--tw-text-opacity": 1,
			"color": "rgb(195 190 247 / var(--tw-text-opacity))"
		}
	},
	"text-black": {
		"style": {
			"--tw-text-opacity": 1,
			"color": "rgb(0 0 0 / var(--tw-text-opacity))"
		}
	},
	"text-dark-500": {
		"style": {
			"--tw-text-opacity": 1,
			"color": "rgb(80 80 80 / var(--tw-text-opacity))"
		}
	},
	"text-white": {
		"style": {
			"--tw-text-opacity": 1,
			"color": "rgb(255 255 255 / var(--tw-text-opacity))"
		}
	}
}